suchyta_utils/__init__.py
suchyta_utils/_dbfunctions.py
suchyta_utils/_jkfunctions.py
suchyta_utils/_mpifunctions.py
suchyta_utils/balrog.py
suchyta_utils/custom-sytle.mpl
suchyta_utils/db.py
suchyta_utils/hp.py
suchyta_utils/jk.py
suchyta_utils/mpi.py
suchyta_utils/plot.py
suchyta_utils/slr.py
suchyta_utils/system.py
suchyta_utils-0.1.1.data/scripts/.screenrc-nest_inner
suchyta_utils-0.1.1.data/scripts/.screenrc-nest_outer
suchyta_utils-0.1.1.data/scripts/catpdfs
suchyta_utils-0.1.1.data/scripts/screen-detach
suchyta_utils-0.1.1.data/scripts/screen-kill
suchyta_utils-0.1.1.data/scripts/screen-retach
suchyta_utils-0.1.1.data/scripts/screen-split
suchyta_utils-0.1.1.dist-info/DESCRIPTION.rst
suchyta_utils-0.1.1.dist-info/METADATA
suchyta_utils-0.1.1.dist-info/RECORD
suchyta_utils-0.1.1.dist-info/WHEEL
suchyta_utils-0.1.1.dist-info/metadata.json
suchyta_utils-0.1.1.dist-info/top_level.txt
