Metadata-Version: 2.0
Name: suchyta-utils
Version: 0.1.1
Summary: Utilities written by Eric Suchyta
Home-page: UNKNOWN
Author: Eric Suchyta
Author-email: eric.d.suchyta@gmail.com
License: GPL
Platform: UNKNOWN
